[
  {"identityNumber" : 221425234, "email" : "windah123@gmail.com", "username" :"windah", "phoneNumber" : 6285164742502, "password" : "password1" },
  {"identityNumber" : 221425534, "email" : "ronaldo123@gmail.com", "username" :"ronaldo123", "phoneNumber" : 6285161743502, "password" : "password2" },
  {"identityNumber" : 221425236, "email" : "ricardo123@gmail.com", "username" :"ricardokaka", "phoneNumber" : 6285161342502, "password" : "password3" },
  {"identityNumber" : 221425230, "email" : "ridwandwip@gmail.com", "username" :"ridwan", "phoneNumber" : 6285153452532, "password" : "password4" }
]